<?xml version="1.0" encoding="utf-8" ?>
<dwsync>
<file name="about.png" local="128131883617656250" remote="128131879620000000" testing="0" />
<file name="browsinfo.png" local="128131883618281250" remote="128131879620000000" testing="0" />
<file name="calc.png" local="128131883618281250" remote="128131879620000000" testing="0" />
<file name="calendar.png" local="128131883618281250" remote="128131879620000000" testing="0" />
<file name="conversioncalc.png" local="128131883618437500" remote="128131879620000000" testing="0" />
<file name="country.png" local="128131883618437500" remote="128131879620000000" testing="0" />
<file name="distance.png" local="128131883618593750" remote="128131879620000000" testing="0" />
<file name="ie.png" local="128131883618593750" remote="128131879620000000" testing="0" />
<file name="paint.png" local="128131883618593750" remote="128131879620000000" testing="0" />
<file name="peri.png" local="128131883618593750" remote="128131879620000000" testing="0" />
<file name="pixfix.png" local="128131883618750000" remote="128131879620000000" testing="0" />
<file name="run.png" local="128131883618750000" remote="128131879620000000" testing="0" />
<file name="states.png" local="128131883618906250" remote="128131879620000000" testing="0" />
<file name="stopwatch.png" local="128131883619062500" remote="128131879620000000" testing="0" />
<file name="texteditor.png" local="128131883619062500" remote="128131879620000000" testing="0" />
<file name="update.png" local="128131883619687500" remote="128131879620000000" testing="0" />
<file name="view.png" local="128131883619687500" remote="128131879620000000" testing="0" />
<file name="Thumbs.db" local="128131883619531250" remote="128131879620000000" testing="0" />
</dwsync>